kogi/OLDai.py
kogi/OLDchat.py
kogi/OLDpan.py
kogi/OLDtransform.py
kogi/__init__.py
kogi/canvas.py
kogi/chat.py
kogi/hook.py
kogi/jwu.py
kogi/trace_error.py
kogi/OLDliberr/emsg_rules.tsv
kogi/problem/__init__.py
kogi/problem/atcoder.py
kogi/problem/drill.py
kogi/problem/judge.py
kogi/problem/testdata.py
kogi/problem/timeout.py
kogi/service/OLDchatgpt.py
kogi/service/OLDflaskapi.py
kogi/service/OLDflaskserv.py
kogi/service/OLDhuggingface.py
kogi/service/__init__.py
kogi/service/chatgpt.py
kogi/service/codellm.py
kogi/service/flaskapi.py
kogi/service/flaskserv.py
kogi/service/globals.py
kogi/service/huggingface.py
kogi/service/s3logging.py
kogi/service/simplemsg.py
kogi/service/simplemsg_ja.tsv
kogi/service/slack.py
kogi/service/textra.py
kogi/webui/__init__.py
kogi/webui/chatgpt-fs8.png
kogi/webui/dialog.css
kogi/webui/dialog.py
kogi/webui/error-fs8.png
kogi/webui/girl-fs8.png
kogi/webui/google_check.py
kogi/webui/keytype.py
kogi/webui/kogi-fs8.png
kogi/webui/kogi_doya-fs8.png
kogi/webui/kogi_error-fs8.png
kogi/webui/kogi_gaan-fs8.png
kogi/webui/kogi_gpt-fs8.png
kogi/webui/kogi_imo-fs8.png
kogi/webui/kogi_panic-fs8.png
kogi/webui/load_content.py
kogi/webui/openai-fs8.png
kogi/webui/pycanvas.py
kogi/webui/robot-fs8.png
kogi/webui/ta-fs8.png
kogi-0.6.11.8.dist-info/LICENSE
kogi-0.6.11.8.dist-info/METADATA
kogi-0.6.11.8.dist-info/WHEEL
kogi-0.6.11.8.dist-info/top_level.txt
kogi-0.6.11.8.dist-info/RECORD
