Metadata-Version: 2.1
Name: kogi
Version: 0.6.11.8
Summary: Kogi Programming Assistant AI Dog
Home-page: https://github.com/kuramitsulab/kogi
Author: Kimio Kuramitsu
License: MIT
Platform: UNKNOWN
Classifier: Development Status :: 4 - Beta
Classifier: License :: OSI Approved :: MIT License
Classifier: Framework :: IPython
Classifier: Programming Language :: Python :: 3.7
Classifier: Programming Language :: Python :: 3.8
Classifier: Programming Language :: Python :: 3.9
Classifier: Programming Language :: Python :: 3.10
Classifier: Intended Audience :: Education
License-File: LICENSE
Requires-Dist: openai (<1.0.0)
Requires-Dist: pegtree
Requires-Dist: requests
Requires-Dist: requests-oauthlib
Requires-Dist: cohere
Requires-Dist: tiktoken
Requires-Dist: markdown
